githubquery/GithubSession.py
githubquery/QueryIterator.py
githubquery/__init__.py
githubquery/bin.py
githubquery/exceptions.py
githubquery/proxies.py
githubquery-1.0.6.dist-info/METADATA
githubquery-1.0.6.dist-info/WHEEL
githubquery-1.0.6.dist-info/entry_points.txt
githubquery-1.0.6.dist-info/top_level.txt
githubquery-1.0.6.dist-info/RECORD
