Metadata-Version: 2.1
Name: githubquery
Version: 1.0.6
Summary: Python wrapper for the github advanced search
Home-page: UNKNOWN
Author: UNKNOWN
Author-email: UNKNOWN
License: UNKNOWN
Platform: UNKNOWN
Requires-Dist: requests
Requires-Dist: bs4
Requires-Dist: fake-useragent
Requires-Dist: click
Requires-Dist: termcolor
